LICENSE.md
MANIFEST.in
README.md
RELEASE_NOTES.txt
pythonql.pth
setup.py
./pythonql/Ast.py
./pythonql/Executor.py
./pythonql/PQTable.py
./pythonql/PQTuple.py
./pythonql/Rewriter.py
./pythonql/RunPYQL.py
./pythonql/__init__.py
./pythonql/helpers.py
./pythonql/pandas_lib.py
./pythonql/codec/__init__.py
./pythonql/codec/register.py
./pythonql/parser/Preprocessor.py
./pythonql/parser/PythonQLLexer.py
./pythonql/parser/PythonQLParser.py
./pythonql/parser/__init__.py
./pythonql/parser/parsertab.py
./pythonql/sources/__init__.py
./pythonql/sources/postgresql.py
./pythonql/sources/source.py
pythonql.egg-info/PKG-INFO
pythonql.egg-info/SOURCES.txt
pythonql.egg-info/dependency_links.txt
pythonql.egg-info/requires.txt
pythonql.egg-info/top_level.txt